iec61850/_iec61850.so
iec61850/__init__.py
iec61850/test_pyiec61850.py
iec61850/iec61850.py
iec61850.libs/libiec61850-08b0b601.so.1.5.1
iec61850-1.5.1.post0.dist-info/WHEEL
iec61850-1.5.1.post0.dist-info/METADATA
iec61850-1.5.1.post0.dist-info/top_level.txt
iec61850-1.5.1.post0.dist-info/COPYING
iec61850-1.5.1.post0.dist-info/RECORD
